README.md
setup.py
benchmark/benchmark_index.R
data/download-info.md
imap/__init__.py
imap/stage1.py
imap/stage2.py
imap.egg-info/PKG-INFO
imap.egg-info/SOURCES.txt
imap.egg-info/dependency_links.txt
imap.egg-info/requires.txt
imap.egg-info/top_level.txt
tutorials/CRC_tutorial.ipynb
tutorials/DC_complete Instructions.ipynb
tutorials/cell_lines_tutorial.ipynb
tutorials/human_cell_atlas_tutorial.ipynb
tutorials/.ipynb_checkpoints/CRC_tutorial-checkpoint.ipynb
tutorials/.ipynb_checkpoints/cell_lines_tutorial-checkpoint.ipynb
tutorials/.ipynb_checkpoints/human_cell_atlas_tutorial-checkpoint.ipynb