Metadata-Version: 2.1
Name: imap
Version: 1.0.0
Summary: The integration of single-cell RNA-sequencing datasets from multiple sources is critical for deciphering cell-cell heterogeneities and interactions in complex biological systems. We present a novel unsupervised batch removal framework, called iMAP, based on two state-of-art deep generative models – autoencoders and generative adversarial networks.
Home-page: https://github.com/Svvord/
Author: Dongfang Wang, Siyu Hou
Author-email: housy17@mails.tsinghua.edu.cn
Maintainer: Siyu Hou
Maintainer-email: housy17@mails.tsinghua.edu.cn
License: MIT Licence
Keywords: single-cell RNA-sequencing technologies,neural network,GAN,batch removal
Platform: any
